multiverses/__init__.py
multiverses/core.py
themultiverse-0.2.0.dist-info/METADATA
themultiverse-0.2.0.dist-info/WHEEL
themultiverse-0.2.0.dist-info/top_level.txt
themultiverse-0.2.0.dist-info/RECORD
