Metadata-Version: 2.4
Name: TheMultiverse
Version: 0.2.0
Summary: A lightweight async multiverse runner with shared state.
Author-email: Lizard Rush <your-email@example.com>
License: MIT
Project-URL: Homepage, https://github.com/yourusername/PyMultiverse
Classifier: Programming Language :: Python :: 3
Classifier: Framework :: AsyncIO
Classifier: License :: OSI Approved :: MIT License
Classifier: Operating System :: OS Independent
Requires-Python: >=3.8
